{
  "info": {
    "name": "Nursery Backend APIs",
    "description": "Postman Collection for Nursery Backend. Includes Auth, Nurseries, Items, Services, Cart, and Orders flow.",
    "schema": "https://schema.getpostman.com/json/collection/v2.1.0/collection.json"
  },
  "item": [
    {
      "name": "1. Authentication",
      "item": [
        {
          "name": "Send OTP",
          "request": {
            "method": "POST",
            "header": [],
            "body": {
              "mode": "raw",
              "raw": "{\n    \"phone\": \"9876543210\"\n}",
              "options": {
                "raw": {
                  "language": "json"
                }
              }
            },
            "url": {
              "raw": "http://localhost:3000/api/auth/send-otp",
              "protocol": "http",
              "host": ["localhost"],
              "port": "3000",
              "path": ["api", "auth", "send-otp"]
            }
          }
        },
        {
          "name": "Verify OTP",
          "request": {
            "method": "POST",
            "header": [],
            "body": {
              "mode": "raw",
              "raw": "{\n    \"phone\": \"9876543210\",\n    \"otp\": \"1234\"\n}",
              "options": {
                "raw": {
                  "language": "json"
                }
              }
            },
            "url": {
              "raw": "http://localhost:3000/api/auth/verify-otp",
              "protocol": "http",
              "host": ["localhost"],
              "port": "3000",
              "path": ["api", "auth", "verify-otp"]
            }
          }
        },
        {
          "name": "Profile Setup",
          "request": {
            "method": "POST",
            "header": [],
            "body": {
              "mode": "raw",
              "raw": "{\n    \"user_id\": \"<<REPLACE_WITH_USER_ID>>\",\n    \"name\": \"Riya Garg\",\n    \"address\": {\n        \"line1\": \"Flat 101, Green Society\",\n        \"city\": \"Noida\",\n        \"state\": \"UP\",\n        \"pincode\": \"201301\"\n    }\n}",
              "options": {
                "raw": {
                  "language": "json"
                }
              }
            },
            "url": {
              "raw": "http://localhost:3000/api/auth/profile-setup",
              "protocol": "http",
              "host": ["localhost"],
              "port": "3000",
              "path": ["api", "auth", "profile-setup"]
            }
          }
        }
      ]
    },
    {
      "name": "2. Home & Nurseries",
      "item": [
        {
          "name": "Homepage Data",
          "request": {
            "method": "GET",
            "header": [],
            "url": {
              "raw": "http://localhost:3000/api/home",
              "protocol": "http",
              "host": ["localhost"],
              "port": "3000",
              "path": ["api", "home"]
            }
          }
        },
        {
          "name": "Global Search",
          "request": {
            "method": "GET",
            "header": [],
            "url": {
              "raw": "http://localhost:3000/api/search?q=rose&type=product",
              "protocol": "http",
              "host": ["localhost"],
              "port": "3000",
              "path": ["api", "search"],
              "query": [
                { "key": "q", "value": "rose" },
                { "key": "type", "value": "product" }
              ]
            }
          }
        },
        {
          "name": "Nearby Nurseries",
          "request": {
            "method": "GET",
            "header": [],
            "url": {
              "raw": "http://localhost:3000/api/nurseries/nearby?lat=28.7&lng=77.1&radius=15",
              "protocol": "http",
              "host": ["localhost"],
              "port": "3000",
              "path": ["api", "nurseries", "nearby"],
              "query": [
                { "key": "lat", "value": "28.7" },
                { "key": "lng", "value": "77.1" },
                { "key": "radius", "value": "15" }
              ]
            }
          }
        },
        {
          "name": "Single Nursery Details (Catalog)",
          "request": {
            "method": "GET",
            "header": [],
            "url": {
              "raw": "http://localhost:3000/api/nurseries/<<REPLACE_WITH_NURSERY_ID>>",
              "protocol": "http",
              "host": ["localhost"],
              "port": "3000",
              "path": ["api", "nurseries", "<<REPLACE_WITH_NURSERY_ID>>"]
            }
          }
        }
      ]
    },
    {
      "name": "3. Items & Services",
      "item": [
        {
          "name": "Fetch All Items (Products)",
          "request": {
            "method": "GET",
            "header": [],
            "url": {
              "raw": "http://localhost:3000/api/products",
              "protocol": "http",
              "host": ["localhost"],
              "port": "3000",
              "path": ["api", "products"]
            }
          }
        },
        {
          "name": "Fetch All Services",
          "request": {
            "method": "GET",
            "header": [],
            "url": {
              "raw": "http://localhost:3000/api/services",
              "protocol": "http",
              "host": ["localhost"],
              "port": "3000",
              "path": ["api", "services"]
            }
          }
        }
      ]
    },
    {
      "name": "4. Cart",
      "item": [
        {
          "name": "Add to Cart",
          "request": {
            "method": "POST",
            "header": [],
            "body": {
              "mode": "raw",
              "raw": "{\n    \"user_id\": \"123\",\n    \"item_id\": \"456\",\n    \"type\": \"product\",\n    \"qty\": 2\n}",
              "options": {
                "raw": {
                  "language": "json"
                }
              }
            },
            "url": {
              "raw": "http://localhost:3000/api/cart/add",
              "protocol": "http",
              "host": ["localhost"],
              "port": "3000",
              "path": ["api", "cart", "add"]
            }
          }
        },
        {
          "name": "Clear Cart",
          "request": {
            "method": "DELETE",
            "header": [],
            "body": {
              "mode": "raw",
              "raw": "{\n    \"user_id\": \"123\"\n}",
              "options": {
                "raw": {
                  "language": "json"
                }
              }
            },
            "url": {
              "raw": "http://localhost:3000/api/cart/clear",
              "protocol": "http",
              "host": ["localhost"],
              "port": "3000",
              "path": ["api", "cart", "clear"]
            }
          }
        },
        {
          "name": "Schedule Service",
          "request": {
            "method": "POST",
            "header": [],
            "body": {
              "mode": "raw",
              "raw": "{\n    \"user_id\": \"123\",\n    \"service_id\": \"789\",\n    \"scheduled_date\": \"2026-05-01\",\n    \"time_slot\": \"10:00 AM\"\n}",
              "options": {
                "raw": {
                  "language": "json"
                }
              }
            },
            "url": {
              "raw": "http://localhost:3000/api/cart/schedule",
              "protocol": "http",
              "host": ["localhost"],
              "port": "3000",
              "path": ["api", "cart", "schedule"]
            }
          }
        },
        {
          "name": "Apply Coupon",
          "request": {
            "method": "POST",
            "header": [],
            "body": {
              "mode": "raw",
              "raw": "{\n    \"user_id\": \"123\",\n    \"code\": \"WELCOME50\"\n}",
              "options": {
                "raw": {
                  "language": "json"
                }
              }
            },
            "url": {
              "raw": "http://localhost:3000/api/cart/apply-coupon",
              "protocol": "http",
              "host": ["localhost"],
              "port": "3000",
              "path": ["api", "cart", "apply-coupon"]
            }
          }
        },
        {
          "name": "Cart Summary",
          "request": {
            "method": "GET",
            "header": [],
            "url": {
              "raw": "http://localhost:3000/api/cart/summary?user_id=123",
              "protocol": "http",
              "host": ["localhost"],
              "port": "3000",
              "path": ["api", "cart", "summary"],
              "query": [
                { "key": "user_id", "value": "123" }
              ]
            }
          }
        }
      ]
    },
    {
      "name": "5. Orders",
      "item": [
        {
          "name": "Create Order",
          "request": {
            "method": "POST",
            "header": [],
            "body": {
              "mode": "raw",
              "raw": "{\n    \"user_id\": \"123\",\n    \"delivery_address\": \"My Saved Address\",\n    \"payment_method\": \"razorpay\"\n}",
              "options": {
                "raw": {
                  "language": "json"
                }
              }
            },
            "url": {
              "raw": "http://localhost:3000/api/orders/create",
              "protocol": "http",
              "host": ["localhost"],
              "port": "3000",
              "path": ["api", "orders", "create"]
            }
          }
        },
        {
          "name": "Verify Payment Webhook",
          "request": {
            "method": "POST",
            "header": [],
            "body": {
              "mode": "raw",
              "raw": "{\n    \"razorpay_order_id\": \"order_abc123\",\n    \"razorpay_payment_id\": \"pay_xyz789\",\n    \"razorpay_signature\": \"signed_hash_string\"\n}",
              "options": {
                "raw": {
                  "language": "json"
                }
              }
            },
            "url": {
              "raw": "http://localhost:3000/api/orders/payment-verify",
              "protocol": "http",
              "host": ["localhost"],
              "port": "3000",
              "path": ["api", "orders", "payment-verify"]
            }
          }
        },
        {
          "name": "My Orders",
          "request": {
            "method": "GET",
            "header": [],
            "url": {
              "raw": "http://localhost:3000/api/orders?user_id=123",
              "protocol": "http",
              "host": ["localhost"],
              "port": "3000",
              "path": ["api", "orders"],
              "query": [
                { "key": "user_id", "value": "123" }
              ]
            }
          }
        },
        {
          "name": "Order Summary / Tracking",
          "request": {
            "method": "GET",
            "header": [],
            "url": {
              "raw": "http://localhost:3000/api/orders/98765",
              "protocol": "http",
              "host": ["localhost"],
              "port": "3000",
              "path": ["api", "orders", "98765"]
            }
          }
        }
      ]
    },
    {
      "name": "6. Profile",
      "item": [
        {
          "name": "Get Profile",
          "request": {
            "method": "GET",
            "header": [],
            "url": {
              "raw": "http://localhost:3000/api/profile?user_id=123",
              "protocol": "http",
              "host": ["localhost"],
              "port": "3000",
              "path": ["api", "profile"],
              "query": [
                { "key": "user_id", "value": "123" }
              ]
            }
          }
        },
        {
          "name": "Update Profile",
          "request": {
            "method": "PATCH",
            "header": [],
            "body": {
              "mode": "raw",
              "raw": "{\n    \"user_id\": \"123\",\n    \"name\": \"Riya Updated\",\n    \"address\": {\n        \"line1\": \"Block A\"\n    }\n}",
              "options": {
                "raw": {
                  "language": "json"
                }
              }
            },
            "url": {
              "raw": "http://localhost:3000/api/profile",
              "protocol": "http",
              "host": ["localhost"],
              "port": "3000",
              "path": ["api", "profile"]
            }
          }
        }
      ]
    }
  ]
}
